idealreport/__init__.py
idealreport/createhtml.py
idealreport/reporter.py
idealreport/template.html
idealreport/htmlLibs/normalize.css
idealreport/htmlLibs/plotly.js
idealreport/htmlLibs/plotly.min.js
idealreport/htmlLibs/plotting.js
idealreport/htmlLibs/raleway-300-400-600.css
idealreport/htmlLibs/skeleton.css
idealreport-0.121.dist-info/DESCRIPTION.rst
idealreport-0.121.dist-info/METADATA
idealreport-0.121.dist-info/RECORD
idealreport-0.121.dist-info/WHEEL
idealreport-0.121.dist-info/metadata.json
idealreport-0.121.dist-info/top_level.txt
